learningdhara/__init__.py
learningdhara/insert.py
learningdhara/select.py
learningdhara-0.1.0.dist-info/METADATA
learningdhara-0.1.0.dist-info/WHEEL
learningdhara-0.1.0.dist-info/RECORD
