Metadata-Version: 2.1
Name: learningdhara
Version: 0.1.0
Summary: Common feature for json data handling
Author: Nishant Ranjan
Author-email: nishant@learningdhara.com
Requires-Python: >=3.11,<4.0
Classifier: Programming Language :: Python :: 3
Classifier: Programming Language :: Python :: 3.11
Classifier: Programming Language :: Python :: 3.12
